{
    "greeting":"Hello",
    "your-name-is":"Your name is",
    "weather": {
        "get-description": "To get the weather, enter the city in Russian or English.",
        "tg-string":"City: {{city}},\nTemp: {{temp}},\nFeels like: {{feel}},\nHumidity: {{humidity}}"
          
        },
        "actions": {
            "reset": {
                "description":"App param does reset!"
            },
            "undefined": {
                "description":"I cant understand!"
            }
        },
    "buttons": {
        "fill-form": "Fill the form",
        "open-app": "Open app",
        "weather": "Weather request",
        "event-reminder": "Event reminder",
        "event-weather": "Event weather",
        "profile": "Profile",
        "reset": "Reset"
    },
    "notifications": {
        "common": {
            "start":"Server started at: {{date}}",
            "new-user":"New user with {{userId}} was created. First name is {{userName}}"
        },
        "errors": {
            "something-went-wrong": "Something went wrong",
            "cant-understand": "I don't understand you.. Let's try again"
        }
    },
    "callback": {
        "request": "What do you want?"
    }
}